ytconverter/__init__.py
ytconverter/__main__.py
ytconverter/config.py
ytconverter/constants.py
ytconverter/version.json
ytconverter/cli/__init__.py
ytconverter/cli/banner.py
ytconverter/cli/menu.py
ytconverter/cli/prompts.py
ytconverter/core/__init__.py
ytconverter/core/bootstrap.py
ytconverter/core/version.py
ytconverter/downloaders/__init__.py
ytconverter/downloaders/base.py
ytconverter/downloaders/multi_mp3.py
ytconverter/downloaders/multi_mp4.py
ytconverter/downloaders/playlist_mp3.py
ytconverter/downloaders/playlist_mp4.py
ytconverter/downloaders/single_mp3.py
ytconverter/downloaders/single_mp4.py
ytconverter/downloaders/downloaders/__init__.py
ytconverter/downloaders/downloaders/base.py
ytconverter/downloaders/downloaders/multi_mp3.py
ytconverter/downloaders/downloaders/multi_mp4.py
ytconverter/downloaders/downloaders/single_mp3.py
ytconverter/downloaders/downloaders/single_mp4.py
ytconverter/utils/__init__.py
ytconverter/utils/platform_.py
ytconverter/utils/sanitize.py
ytconverter/utils/styling.py
ytconverter/utils/update.py
ytconverter-4.0.3.0.dist-info/entry_points.txt
ytconverter-4.0.3.0.dist-info/licenses/LICENSE
ytconverter-4.0.3.0.dist-info/WHEEL
ytconverter-4.0.3.0.dist-info/METADATA
ytconverter-4.0.3.0.dist-info/RECORD
