Metadata-Version: 2.4
Name: ytconverter
Version: 4.0.3.0
Summary: Terminal-based YouTube video/audio downloader using yt-dlp and ffmpeg
Keywords: youtube,downloader,yt-dlp,ffmpeg,terminal,audio,video,python,youtube-downloader
Author-email: Kaif <kafcodec@gmail.com>
Requires-Python: >=3.7
License-File: LICENSE
Requires-Dist: yt-dlp
Requires-Dist: ffmpeg-python
Requires-Dist: colored
Requires-Dist: fontstyle
Requires-Dist: httpx
Project-URL: Homepage, https://github.com/kaifcodec/ytconverter
